executable_application/__init__.py
executable_application-0.3.0.dist-info/METADATA
executable_application-0.3.0.dist-info/WHEEL
executable_application-0.3.0.dist-info/entry_points.txt
executable_application-0.3.0.dist-info/RECORD
