Metadata-Version: 2.4
Name: executable-application
Version: 0.3.0
Summary: An example of an executable application.
Author-email: Charlie Marsh <hey@astral.sh>
Requires-Python: >=3.8
